byted_overpass_ad_sco_smart_creative/__init__.py
byted_overpass_ad_sco_smart_creative-0.0.1.dist-info/METADATA
byted_overpass_ad_sco_smart_creative-0.0.1.dist-info/WHEEL
byted_overpass_ad_sco_smart_creative-0.0.1.dist-info/top_level.txt
byted_overpass_ad_sco_smart_creative-0.0.1.dist-info/RECORD
